CHANGELOG.rst
LICENSE
LICENSE-3RD-PARTY
MANIFEST.in
NOTICE
README.rst
setup.py
vcloudair/__init__.py
vcloudair/ans.py
vcloudair/dr.py
vcloudair/metrics.py
vcloudair/query.py
vcloudair/session.py
vcloudair/util.py
vcloudair.egg-info/PKG-INFO
vcloudair.egg-info/SOURCES.txt
vcloudair.egg-info/dependency_links.txt
vcloudair.egg-info/not-zip-safe
vcloudair.egg-info/requires.txt
vcloudair.egg-info/top_level.txt